beetsplug/__init__.py
beetsplug/autogenre/__init__.py
beetsplug/autogenre/config_default.yaml
beetsplug/autogenre/genretree.py
beets_autogenre-0.5.1.dist-info/LICENSE
beets_autogenre-0.5.1.dist-info/METADATA
beets_autogenre-0.5.1.dist-info/WHEEL
beets_autogenre-0.5.1.dist-info/top_level.txt
beets_autogenre-0.5.1.dist-info/RECORD
