Metadata-Version: 2.1
Name: beets-autogenre
Version: 0.5.1
Summary: Detect the genres for each song within your beets library
Home-page: https://github.com/mgoltzsche/beets-autogenre
Author: Max Goltzsche
License: UNKNOWN
Platform: UNKNOWN
Classifier: Programming Language :: Python :: 3.6
Classifier: License :: OSI Approved :: Apache Software License
Classifier: Operating System :: OS Independent
License-File: LICENSE
Requires-Dist: beets
Requires-Dist: pylast
Requires-Dist: pyyaml
